redshift_pandas-0.1.1.dist-info/DESCRIPTION.rst
redshift_pandas-0.1.1.dist-info/METADATA
redshift_pandas-0.1.1.dist-info/RECORD
redshift_pandas-0.1.1.dist-info/WHEEL
redshift_pandas-0.1.1.dist-info/metadata.json
redshift_pandas-0.1.1.dist-info/top_level.txt
redshiftpandas/__init__.py
redshiftpandas/date_functions.py
redshiftpandas/example.py
