Metadata-Version: 2.0
Name: redshift-pandas
Version: 0.1.1
Summary: Redshift functions written in Python
Home-page: https://github.com/thibaulthe/redshift-pandas
Author: Thibault He
Author-email: thibault.he@gmail.com
License: UNKNOWN
Platform: UNKNOWN
